siqc/__init__.py
siqc/siqc.py
siqc-0.0.5.dist-info/LICENSE
siqc-0.0.5.dist-info/METADATA
siqc-0.0.5.dist-info/WHEEL
siqc-0.0.5.dist-info/top_level.txt
siqc-0.0.5.dist-info/RECORD
