Metadata-Version: 2.1
Name: siqc
Version: 0.0.5
Summary: siqc
Home-page: https://github.com/alex-reardon/siqc
Author: Reardon, Fonville, Avants
Author-email: areardon@invicro.com
License: UNKNOWN
Platform: UNKNOWN
License-File: LICENSE
